dopynion/__init__.py
dopynion/__main__.py
dopynion/cards.py
dopynion/constants.py
dopynion/data_model.py
dopynion/exceptions.py
dopynion/game.py
dopynion/player.py
dopynion/py.typed
dopynion/record.py
dopynion-0.9.2.dist-info/licenses/LICENSE
dopynion-0.9.2.dist-info/METADATA
dopynion-0.9.2.dist-info/WHEEL
dopynion-0.9.2.dist-info/top_level.txt
dopynion-0.9.2.dist-info/RECORD
