Metadata-Version: 2.4
Name: dopynion
Version: 0.9.2
Summary: Dopynion
Requires-Python: >=3.12
License-File: LICENSE
Requires-Dist: pydantic
Requires-Dist: tzdata
Dynamic: license-file
